README.md
setup.py
pulumi_ctfd/__init__.py
pulumi_ctfd/_inputs.py
pulumi_ctfd/_utilities.py
pulumi_ctfd/challenge.py
pulumi_ctfd/get_challenges.py
pulumi_ctfd/get_teams.py
pulumi_ctfd/get_users.py
pulumi_ctfd/outputs.py
pulumi_ctfd/provider.py
pulumi_ctfd/pulumi-plugin.json
pulumi_ctfd/py.typed
pulumi_ctfd/team.py
pulumi_ctfd/user.py
pulumi_ctfd.egg-info/PKG-INFO
pulumi_ctfd.egg-info/SOURCES.txt
pulumi_ctfd.egg-info/dependency_links.txt
pulumi_ctfd.egg-info/not-zip-safe
pulumi_ctfd.egg-info/requires.txt
pulumi_ctfd.egg-info/top_level.txt
pulumi_ctfd/config/__init__.py
pulumi_ctfd/config/vars.py