Metadata-Version: 2.1
Name: pulumi-ctfd
Version: 0.1.17
Summary: The CTFd provider for Pulumi, to manage its resources as code.
Home-page: https://ctfer.io
License: Apache-2.0
Project-URL: Repository, https://github.com/ctfer-io/pulumi-ctfd
Keywords: pulumi ctfd category/cloud
Platform: UNKNOWN
Requires-Python: >=3.8
